mylib1991/__init__.py
mylib1991-0.1.dist-info/LICENSE.txt
mylib1991-0.1.dist-info/METADATA
mylib1991-0.1.dist-info/WHEEL
mylib1991-0.1.dist-info/top_level.txt
mylib1991-0.1.dist-info/RECORD
