Metadata-Version: 2.1
Name: mylib1991
Version: 0.1
Summary: for Normal print
Author: Pratik Awasarmol
Author-email: pratikawasarmol883@gmail.com
Classifier: Programming Language :: Python :: 3
Classifier: License :: OSI Approved :: MIT License
Classifier: Operating System :: OS Independent
License-File: LICENSE.txt
